[
  {
    "type": "type",
    "name": "program.reference",
    "value": {
      "type": "object",
      "attributes": {
        "_ref": {
          "type": "objectAttribute",
          "value": {
            "type": "string"
          }
        },
        "_type": {
          "type": "objectAttribute",
          "value": {
            "type": "string",
            "value": "reference"
          }
        },
        "_weak": {
          "type": "objectAttribute",
          "value": {
            "type": "boolean"
          },
          "optional": true
        }
      },
      "dereferencesTo": "program"
    }
  },
  {
    "name": "programSponsorPackage",
    "type": "document",
    "attributes": {
      "_id": {
        "type": "objectAttribute",
        "value": {
          "type": "string"
        }
      },
      "_type": {
        "type": "objectAttribute",
        "value": {
          "type": "string",
          "value": "programSponsorPackage"
        }
      },
      "_createdAt": {
        "type": "objectAttribute",
        "value": {
          "type": "string"
        }
      },
      "_updatedAt": {
        "type": "objectAttribute",
        "value": {
          "type": "string"
        }
      },
      "_rev": {
        "type": "objectAttribute",
        "value": {
          "type": "string"
        }
      },
      "program": {
        "type": "objectAttribute",
        "value": {
          "type": "inline",
          "name": "program.reference"
        },
        "optional": true
      },
      "tierName": {
        "type": "objectAttribute",
        "value": {
          "type": "string"
        },
        "optional": true
      },
      "tierGroup": {
        "type": "objectAttribute",
        "value": {
          "type": "union",
          "of": [
            {
              "type": "string",
              "value": "Title Sponsor"
            },
            {
              "type": "string",
              "value": "Tier 1"
            },
            {
              "type": "string",
              "value": "Tier 2"
            },
            {
              "type": "string",
              "value": "Tier 3"
            },
            {
              "type": "string",
              "value": "3-Month Package"
            }
          ]
        },
        "optional": true
      },
      "price": {
        "type": "objectAttribute",
        "value": {
          "type": "number"
        },
        "optional": true
      },
      "priceDisplay": {
        "type": "objectAttribute",
        "value": {
          "type": "string"
        },
        "optional": true
      },
      "deliverables": {
        "type": "objectAttribute",
        "value": {
          "type": "array",
          "of": {
            "type": "string"
          }
        },
        "optional": true
      },
      "boothSize": {
        "type": "objectAttribute",
        "value": {
          "type": "string"
        },
        "optional": true
      },
      "maxSponsors": {
        "type": "objectAttribute",
        "value": {
          "type": "number"
        },
        "optional": true
      },
      "bloomerangFormUrl": {
        "type": "objectAttribute",
        "value": {
          "type": "string"
        },
        "optional": true
      },
      "sortOrder": {
        "type": "objectAttribute",
        "value": {
          "type": "number"
        },
        "optional": true
      },
      "active": {
        "type": "objectAttribute",
        "value": {
          "type": "boolean"
        },
        "optional": true
      },
      "featured": {
        "type": "objectAttribute",
        "value": {
          "type": "boolean"
        },
        "optional": true
      }
    }
  },
  {
    "name": "siteContent",
    "type": "document",
    "attributes": {
      "_id": {
        "type": "objectAttribute",
        "value": {
          "type": "string"
        }
      },
      "_type": {
        "type": "objectAttribute",
        "value": {
          "type": "string",
          "value": "siteContent"
        }
      },
      "_createdAt": {
        "type": "objectAttribute",
        "value": {
          "type": "string"
        }
      },
      "_updatedAt": {
        "type": "objectAttribute",
        "value": {
          "type": "string"
        }
      },
      "_rev": {
        "type": "objectAttribute",
        "value": {
          "type": "string"
        }
      },
      "page": {
        "type": "objectAttribute",
        "value": {
          "type": "union",
          "of": [
            {
              "type": "string",
              "value": "homepage"
            },
            {
              "type": "string",
              "value": "about"
            },
            {
              "type": "string",
              "value": "programs"
            },
            {
              "type": "string",
              "value": "impact"
            },
            {
              "type": "string",
              "value": "awards"
            },
            {
              "type": "string",
              "value": "partners"
            },
            {
              "type": "string",
              "value": "get-involved"
            },
            {
              "type": "string",
              "value": "contact"
            },
            {
              "type": "string",
              "value": "fire-relief"
            },
            {
              "type": "string",
              "value": "events"
            }
          ]
        },
        "optional": true
      },
      "section": {
        "type": "objectAttribute",
        "value": {
          "type": "string"
        },
        "optional": true
      },
      "headline": {
        "type": "objectAttribute",
        "value": {
          "type": "string"
        },
        "optional": true
      },
      "subheadline": {
        "type": "objectAttribute",
        "value": {
          "type": "string"
        },
        "optional": true
      },
      "body": {
        "type": "objectAttribute",
        "value": {
          "type": "string"
        },
        "optional": true
      },
      "ctaText": {
        "type": "objectAttribute",
        "value": {
          "type": "string"
        },
        "optional": true
      },
      "ctaHref": {
        "type": "objectAttribute",
        "value": {
          "type": "string"
        },
        "optional": true
      }
    }
  },
  {
    "name": "newsMedia",
    "type": "document",
    "attributes": {
      "_id": {
        "type": "objectAttribute",
        "value": {
          "type": "string"
        }
      },
      "_type": {
        "type": "objectAttribute",
        "value": {
          "type": "string",
          "value": "newsMedia"
        }
      },
      "_createdAt": {
        "type": "objectAttribute",
        "value": {
          "type": "string"
        }
      },
      "_updatedAt": {
        "type": "objectAttribute",
        "value": {
          "type": "string"
        }
      },
      "_rev": {
        "type": "objectAttribute",
        "value": {
          "type": "string"
        }
      },
      "outlet": {
        "type": "objectAttribute",
        "value": {
          "type": "string"
        },
        "optional": true
      },
      "title": {
        "type": "objectAttribute",
        "value": {
          "type": "string"
        },
        "optional": true
      },
      "date": {
        "type": "objectAttribute",
        "value": {
          "type": "string"
        },
        "optional": true
      },
      "coverageType": {
        "type": "objectAttribute",
        "value": {
          "type": "union",
          "of": [
            {
              "type": "string",
              "value": "TV"
            },
            {
              "type": "string",
              "value": "Print"
            },
            {
              "type": "string",
              "value": "Online"
            },
            {
              "type": "string",
              "value": "Radio"
            },
            {
              "type": "string",
              "value": "Social"
            },
            {
              "type": "string",
              "value": "Podcast"
            }
          ]
        },
        "optional": true
      },
      "topic": {
        "type": "objectAttribute",
        "value": {
          "type": "string"
        },
        "optional": true
      },
      "url": {
        "type": "objectAttribute",
        "value": {
          "type": "string"
        },
        "optional": true
      },
      "featured": {
        "type": "objectAttribute",
        "value": {
          "type": "boolean"
        },
        "optional": true
      }
    }
  },
  {
    "name": "sponsorTier",
    "type": "document",
    "attributes": {
      "_id": {
        "type": "objectAttribute",
        "value": {
          "type": "string"
        }
      },
      "_type": {
        "type": "objectAttribute",
        "value": {
          "type": "string",
          "value": "sponsorTier"
        }
      },
      "_createdAt": {
        "type": "objectAttribute",
        "value": {
          "type": "string"
        }
      },
      "_updatedAt": {
        "type": "objectAttribute",
        "value": {
          "type": "string"
        }
      },
      "_rev": {
        "type": "objectAttribute",
        "value": {
          "type": "string"
        }
      },
      "title": {
        "type": "objectAttribute",
        "value": {
          "type": "string"
        },
        "optional": true
      },
      "amount": {
        "type": "objectAttribute",
        "value": {
          "type": "string"
        },
        "optional": true
      },
      "description": {
        "type": "objectAttribute",
        "value": {
          "type": "string"
        },
        "optional": true
      },
      "sortOrder": {
        "type": "objectAttribute",
        "value": {
          "type": "number"
        },
        "optional": true
      }
    }
  },
  {
    "type": "type",
    "name": "sanity.imageAsset.reference",
    "value": {
      "type": "object",
      "attributes": {
        "_ref": {
          "type": "objectAttribute",
          "value": {
            "type": "string"
          }
        },
        "_type": {
          "type": "objectAttribute",
          "value": {
            "type": "string",
            "value": "reference"
          }
        },
        "_weak": {
          "type": "objectAttribute",
          "value": {
            "type": "boolean"
          },
          "optional": true
        }
      },
      "dereferencesTo": "sanity.imageAsset"
    }
  },
  {
    "name": "partner",
    "type": "document",
    "attributes": {
      "_id": {
        "type": "objectAttribute",
        "value": {
          "type": "string"
        }
      },
      "_type": {
        "type": "objectAttribute",
        "value": {
          "type": "string",
          "value": "partner"
        }
      },
      "_createdAt": {
        "type": "objectAttribute",
        "value": {
          "type": "string"
        }
      },
      "_updatedAt": {
        "type": "objectAttribute",
        "value": {
          "type": "string"
        }
      },
      "_rev": {
        "type": "objectAttribute",
        "value": {
          "type": "string"
        }
      },
      "title": {
        "type": "objectAttribute",
        "value": {
          "type": "string"
        },
        "optional": true
      },
      "category": {
        "type": "objectAttribute",
        "value": {
          "type": "union",
          "of": [
            {
              "type": "string",
              "value": "Financial & Foundation"
            },
            {
              "type": "string",
              "value": "Brand & In-Kind"
            },
            {
              "type": "string",
              "value": "Government & Civic"
            },
            {
              "type": "string",
              "value": "Education"
            },
            {
              "type": "string",
              "value": "Health & Wellness"
            },
            {
              "type": "string",
              "value": "Community & Crisis"
            },
            {
              "type": "string",
              "value": "Food & Resource"
            },
            {
              "type": "string",
              "value": "Media & Entertainment"
            },
            {
              "type": "string",
              "value": "Operations Support"
            }
          ]
        },
        "optional": true
      },
      "partnerType": {
        "type": "objectAttribute",
        "value": {
          "type": "string"
        },
        "optional": true
      },
      "pillar": {
        "type": "objectAttribute",
        "value": {
          "type": "string"
        },
        "optional": true
      },
      "programsEvents": {
        "type": "objectAttribute",
        "value": {
          "type": "string"
        },
        "optional": true
      },
      "tier": {
        "type": "objectAttribute",
        "value": {
          "type": "union",
          "of": [
            {
              "type": "string",
              "value": "Major"
            },
            {
              "type": "string",
              "value": "Key"
            },
            {
              "type": "string",
              "value": "Supporting"
            },
            {
              "type": "string",
              "value": "Community"
            }
          ]
        },
        "optional": true
      },
      "featuredOnWebsite": {
        "type": "objectAttribute",
        "value": {
          "type": "boolean"
        },
        "optional": true
      },
      "logo": {
        "type": "objectAttribute",
        "value": {
          "type": "object",
          "attributes": {
            "asset": {
              "type": "objectAttribute",
              "value": {
                "type": "inline",
                "name": "sanity.imageAsset.reference"
              },
              "optional": true
            },
            "media": {
              "type": "objectAttribute",
              "value": {
                "type": "unknown"
              },
              "optional": true
            },
            "hotspot": {
              "type": "objectAttribute",
              "value": {
                "type": "inline",
                "name": "sanity.imageHotspot"
              },
              "optional": true
            },
            "crop": {
              "type": "objectAttribute",
              "value": {
                "type": "inline",
                "name": "sanity.imageCrop"
              },
              "optional": true
            },
            "_type": {
              "type": "objectAttribute",
              "value": {
                "type": "string",
                "value": "image"
              }
            }
          }
        },
        "optional": true
      },
      "url": {
        "type": "objectAttribute",
        "value": {
          "type": "string"
        },
        "optional": true
      }
    }
  },
  {
    "name": "sanity.imageCrop",
    "type": "type",
    "value": {
      "type": "object",
      "attributes": {
        "_type": {
          "type": "objectAttribute",
          "value": {
            "type": "string",
            "value": "sanity.imageCrop"
          }
        },
        "top": {
          "type": "objectAttribute",
          "value": {
            "type": "number"
          },
          "optional": true
        },
        "bottom": {
          "type": "objectAttribute",
          "value": {
            "type": "number"
          },
          "optional": true
        },
        "left": {
          "type": "objectAttribute",
          "value": {
            "type": "number"
          },
          "optional": true
        },
        "right": {
          "type": "objectAttribute",
          "value": {
            "type": "number"
          },
          "optional": true
        }
      }
    }
  },
  {
    "name": "sanity.imageHotspot",
    "type": "type",
    "value": {
      "type": "object",
      "attributes": {
        "_type": {
          "type": "objectAttribute",
          "value": {
            "type": "string",
            "value": "sanity.imageHotspot"
          }
        },
        "x": {
          "type": "objectAttribute",
          "value": {
            "type": "number"
          },
          "optional": true
        },
        "y": {
          "type": "objectAttribute",
          "value": {
            "type": "number"
          },
          "optional": true
        },
        "height": {
          "type": "objectAttribute",
          "value": {
            "type": "number"
          },
          "optional": true
        },
        "width": {
          "type": "objectAttribute",
          "value": {
            "type": "number"
          },
          "optional": true
        }
      }
    }
  },
  {
    "name": "orgTimeline",
    "type": "document",
    "attributes": {
      "_id": {
        "type": "objectAttribute",
        "value": {
          "type": "string"
        }
      },
      "_type": {
        "type": "objectAttribute",
        "value": {
          "type": "string",
          "value": "orgTimeline"
        }
      },
      "_createdAt": {
        "type": "objectAttribute",
        "value": {
          "type": "string"
        }
      },
      "_updatedAt": {
        "type": "objectAttribute",
        "value": {
          "type": "string"
        }
      },
      "_rev": {
        "type": "objectAttribute",
        "value": {
          "type": "string"
        }
      },
      "year": {
        "type": "objectAttribute",
        "value": {
          "type": "number"
        },
        "optional": true
      },
      "title": {
        "type": "objectAttribute",
        "value": {
          "type": "string"
        },
        "optional": true
      },
      "detail": {
        "type": "objectAttribute",
        "value": {
          "type": "string"
        },
        "optional": true
      },
      "pillar": {
        "type": "objectAttribute",
        "value": {
          "type": "string"
        },
        "optional": true
      },
      "sortOrder": {
        "type": "objectAttribute",
        "value": {
          "type": "number"
        },
        "optional": true
      }
    }
  },
  {
    "name": "award",
    "type": "document",
    "attributes": {
      "_id": {
        "type": "objectAttribute",
        "value": {
          "type": "string"
        }
      },
      "_type": {
        "type": "objectAttribute",
        "value": {
          "type": "string",
          "value": "award"
        }
      },
      "_createdAt": {
        "type": "objectAttribute",
        "value": {
          "type": "string"
        }
      },
      "_updatedAt": {
        "type": "objectAttribute",
        "value": {
          "type": "string"
        }
      },
      "_rev": {
        "type": "objectAttribute",
        "value": {
          "type": "string"
        }
      },
      "title": {
        "type": "objectAttribute",
        "value": {
          "type": "string"
        },
        "optional": true
      },
      "presentedBy": {
        "type": "objectAttribute",
        "value": {
          "type": "string"
        },
        "optional": true
      },
      "year": {
        "type": "objectAttribute",
        "value": {
          "type": "number"
        },
        "optional": true
      },
      "date": {
        "type": "objectAttribute",
        "value": {
          "type": "string"
        },
        "optional": true
      },
      "context": {
        "type": "objectAttribute",
        "value": {
          "type": "string"
        },
        "optional": true
      },
      "notes": {
        "type": "objectAttribute",
        "value": {
          "type": "string"
        },
        "optional": true
      },
      "level": {
        "type": "objectAttribute",
        "value": {
          "type": "union",
          "of": [
            {
              "type": "string",
              "value": "Federal"
            },
            {
              "type": "string",
              "value": "State Assembly"
            },
            {
              "type": "string",
              "value": "State Senate"
            },
            {
              "type": "string",
              "value": "County"
            },
            {
              "type": "string",
              "value": "City"
            },
            {
              "type": "string",
              "value": "Institutional"
            },
            {
              "type": "string",
              "value": "Nonprofit Partnership"
            },
            {
              "type": "string",
              "value": "Media"
            }
          ]
        },
        "optional": true
      },
      "program": {
        "type": "objectAttribute",
        "value": {
          "type": "inline",
          "name": "program.reference"
        },
        "optional": true
      }
    }
  },
  {
    "name": "impactStat",
    "type": "document",
    "attributes": {
      "_id": {
        "type": "objectAttribute",
        "value": {
          "type": "string"
        }
      },
      "_type": {
        "type": "objectAttribute",
        "value": {
          "type": "string",
          "value": "impactStat"
        }
      },
      "_createdAt": {
        "type": "objectAttribute",
        "value": {
          "type": "string"
        }
      },
      "_updatedAt": {
        "type": "objectAttribute",
        "value": {
          "type": "string"
        }
      },
      "_rev": {
        "type": "objectAttribute",
        "value": {
          "type": "string"
        }
      },
      "value": {
        "type": "objectAttribute",
        "value": {
          "type": "string"
        },
        "optional": true
      },
      "label": {
        "type": "objectAttribute",
        "value": {
          "type": "string"
        },
        "optional": true
      },
      "year": {
        "type": "objectAttribute",
        "value": {
          "type": "union",
          "of": [
            {
              "type": "string",
              "value": "2025"
            },
            {
              "type": "string",
              "value": "Cumulative"
            }
          ]
        },
        "optional": true
      },
      "category": {
        "type": "objectAttribute",
        "value": {
          "type": "string"
        },
        "optional": true
      },
      "sortOrder": {
        "type": "objectAttribute",
        "value": {
          "type": "number"
        },
        "optional": true
      },
      "displayOnWebsite": {
        "type": "objectAttribute",
        "value": {
          "type": "boolean"
        },
        "optional": true
      },
      "context": {
        "type": "objectAttribute",
        "value": {
          "type": "string"
        },
        "optional": true
      },
      "source": {
        "type": "objectAttribute",
        "value": {
          "type": "string"
        },
        "optional": true
      }
    }
  },
  {
    "name": "pillar",
    "type": "document",
    "attributes": {
      "_id": {
        "type": "objectAttribute",
        "value": {
          "type": "string"
        }
      },
      "_type": {
        "type": "objectAttribute",
        "value": {
          "type": "string",
          "value": "pillar"
        }
      },
      "_createdAt": {
        "type": "objectAttribute",
        "value": {
          "type": "string"
        }
      },
      "_updatedAt": {
        "type": "objectAttribute",
        "value": {
          "type": "string"
        }
      },
      "_rev": {
        "type": "objectAttribute",
        "value": {
          "type": "string"
        }
      },
      "pillarName": {
        "type": "objectAttribute",
        "value": {
          "type": "string"
        },
        "optional": true
      },
      "tagline": {
        "type": "objectAttribute",
        "value": {
          "type": "string"
        },
        "optional": true
      },
      "pageDescription": {
        "type": "objectAttribute",
        "value": {
          "type": "string"
        },
        "optional": true
      },
      "headlineStat": {
        "type": "objectAttribute",
        "value": {
          "type": "string"
        },
        "optional": true
      },
      "keyMetric": {
        "type": "objectAttribute",
        "value": {
          "type": "string"
        },
        "optional": true
      },
      "sortOrder": {
        "type": "objectAttribute",
        "value": {
          "type": "number"
        },
        "optional": true
      }
    }
  },
  {
    "name": "event",
    "type": "document",
    "attributes": {
      "_id": {
        "type": "objectAttribute",
        "value": {
          "type": "string"
        }
      },
      "_type": {
        "type": "objectAttribute",
        "value": {
          "type": "string",
          "value": "event"
        }
      },
      "_createdAt": {
        "type": "objectAttribute",
        "value": {
          "type": "string"
        }
      },
      "_updatedAt": {
        "type": "objectAttribute",
        "value": {
          "type": "string"
        }
      },
      "_rev": {
        "type": "objectAttribute",
        "value": {
          "type": "string"
        }
      },
      "title": {
        "type": "objectAttribute",
        "value": {
          "type": "string"
        },
        "optional": true
      },
      "jobNumber": {
        "type": "objectAttribute",
        "value": {
          "type": "string"
        },
        "optional": true
      },
      "program": {
        "type": "objectAttribute",
        "value": {
          "type": "inline",
          "name": "program.reference"
        },
        "optional": true
      },
      "pillar": {
        "type": "objectAttribute",
        "value": {
          "type": "union",
          "of": [
            {
              "type": "string",
              "value": "Crisis & Disaster Stabilization"
            },
            {
              "type": "string",
              "value": "School & Youth Stability"
            },
            {
              "type": "string",
              "value": "Community Health & Resource Access"
            }
          ]
        },
        "optional": true
      },
      "year": {
        "type": "objectAttribute",
        "value": {
          "type": "number"
        },
        "optional": true
      },
      "dateStart": {
        "type": "objectAttribute",
        "value": {
          "type": "string"
        },
        "optional": true
      },
      "dateEnd": {
        "type": "objectAttribute",
        "value": {
          "type": "string"
        },
        "optional": true
      },
      "location": {
        "type": "objectAttribute",
        "value": {
          "type": "string"
        },
        "optional": true
      },
      "description": {
        "type": "objectAttribute",
        "value": {
          "type": "string"
        },
        "optional": true
      },
      "proofStats": {
        "type": "objectAttribute",
        "value": {
          "type": "string"
        },
        "optional": true
      },
      "status": {
        "type": "objectAttribute",
        "value": {
          "type": "union",
          "of": [
            {
              "type": "string",
              "value": "Closed"
            },
            {
              "type": "string",
              "value": "Active"
            },
            {
              "type": "string",
              "value": "Upcoming"
            },
            {
              "type": "string",
              "value": "Cancelled"
            }
          ]
        },
        "optional": true
      },
      "category": {
        "type": "objectAttribute",
        "value": {
          "type": "string"
        },
        "optional": true
      },
      "featured": {
        "type": "objectAttribute",
        "value": {
          "type": "boolean"
        },
        "optional": true
      },
      "displayOnWebsite": {
        "type": "objectAttribute",
        "value": {
          "type": "boolean"
        },
        "optional": true
      },
      "shortDescription": {
        "type": "objectAttribute",
        "value": {
          "type": "string"
        },
        "optional": true
      },
      "galleryImages": {
        "type": "objectAttribute",
        "value": {
          "type": "array",
          "of": {
            "type": "object",
            "attributes": {
              "asset": {
                "type": "objectAttribute",
                "value": {
                  "type": "inline",
                  "name": "sanity.imageAsset.reference"
                },
                "optional": true
              },
              "media": {
                "type": "objectAttribute",
                "value": {
                  "type": "unknown"
                },
                "optional": true
              },
              "hotspot": {
                "type": "objectAttribute",
                "value": {
                  "type": "inline",
                  "name": "sanity.imageHotspot"
                },
                "optional": true
              },
              "crop": {
                "type": "objectAttribute",
                "value": {
                  "type": "inline",
                  "name": "sanity.imageCrop"
                },
                "optional": true
              },
              "caption": {
                "type": "objectAttribute",
                "value": {
                  "type": "string"
                },
                "optional": true
              },
              "_type": {
                "type": "objectAttribute",
                "value": {
                  "type": "string",
                  "value": "image"
                }
              }
            },
            "rest": {
              "type": "object",
              "attributes": {
                "_key": {
                  "type": "objectAttribute",
                  "value": {
                    "type": "string"
                  }
                }
              }
            }
          }
        },
        "optional": true
      },
      "rsvpUrl": {
        "type": "objectAttribute",
        "value": {
          "type": "string"
        },
        "optional": true
      },
      "waysToGetInvolved": {
        "type": "objectAttribute",
        "value": {
          "type": "union",
          "of": [
            {
              "type": "string",
              "value": "Volunteer"
            },
            {
              "type": "string",
              "value": "Donate"
            },
            {
              "type": "string",
              "value": "Sponsor"
            },
            {
              "type": "string",
              "value": "Attend"
            },
            {
              "type": "string",
              "value": "Lunchtime Takeover"
            },
            {
              "type": "string",
              "value": "Resource Fair"
            },
            {
              "type": "string",
              "value": "Parent Empowerment Workshop"
            },
            {
              "type": "string",
              "value": "Parent Empowerment Series"
            },
            {
              "type": "string",
              "value": "Professional Development"
            },
            {
              "type": "string",
              "value": "Staff Appreciation"
            },
            {
              "type": "string",
              "value": "Young Community Builder Program Series"
            },
            {
              "type": "string",
              "value": "Building Community Builders Workshop & Retreat"
            }
          ]
        },
        "optional": true
      },
      "internalBudget": {
        "type": "objectAttribute",
        "value": {
          "type": "number"
        },
        "optional": true
      },
      "internalNotes": {
        "type": "objectAttribute",
        "value": {
          "type": "string"
        },
        "optional": true
      },
      "internalComms": {
        "type": "objectAttribute",
        "value": {
          "type": "string"
        },
        "optional": true
      },
      "contractStatus": {
        "type": "objectAttribute",
        "value": {
          "type": "union",
          "of": [
            {
              "type": "string",
              "value": "New"
            },
            {
              "type": "string",
              "value": "Quote Sent"
            },
            {
              "type": "string",
              "value": "Follow Up needed"
            },
            {
              "type": "string",
              "value": "Invoiced"
            },
            {
              "type": "string",
              "value": "PO Issued"
            },
            {
              "type": "string",
              "value": "Accepted-In Procurement"
            },
            {
              "type": "string",
              "value": "Complete / Archive"
            },
            {
              "type": "string",
              "value": "Pass"
            },
            {
              "type": "string",
              "value": "Evaluating"
            },
            {
              "type": "string",
              "value": "Cancelled"
            }
          ]
        },
        "optional": true
      },
      "poNumber": {
        "type": "objectAttribute",
        "value": {
          "type": "string"
        },
        "optional": true
      },
      "contractAmount": {
        "type": "objectAttribute",
        "value": {
          "type": "number"
        },
        "optional": true
      }
    }
  },
  {
    "name": "program",
    "type": "document",
    "attributes": {
      "_id": {
        "type": "objectAttribute",
        "value": {
          "type": "string"
        }
      },
      "_type": {
        "type": "objectAttribute",
        "value": {
          "type": "string",
          "value": "program"
        }
      },
      "_createdAt": {
        "type": "objectAttribute",
        "value": {
          "type": "string"
        }
      },
      "_updatedAt": {
        "type": "objectAttribute",
        "value": {
          "type": "string"
        }
      },
      "_rev": {
        "type": "objectAttribute",
        "value": {
          "type": "string"
        }
      },
      "title": {
        "type": "objectAttribute",
        "value": {
          "type": "string"
        },
        "optional": true
      },
      "slug": {
        "type": "objectAttribute",
        "value": {
          "type": "inline",
          "name": "slug"
        },
        "optional": true
      },
      "pillar": {
        "type": "objectAttribute",
        "value": {
          "type": "union",
          "of": [
            {
              "type": "string",
              "value": "Crisis & Disaster Stabilization"
            },
            {
              "type": "string",
              "value": "School & Youth Stability"
            },
            {
              "type": "string",
              "value": "Community Health & Resource Access"
            }
          ]
        },
        "optional": true
      },
      "tagline": {
        "type": "objectAttribute",
        "value": {
          "type": "string"
        },
        "optional": true
      },
      "description": {
        "type": "objectAttribute",
        "value": {
          "type": "string"
        },
        "optional": true
      },
      "proofStats": {
        "type": "objectAttribute",
        "value": {
          "type": "string"
        },
        "optional": true
      },
      "allTimeServed": {
        "type": "objectAttribute",
        "value": {
          "type": "string"
        },
        "optional": true
      },
      "volunteerUrl": {
        "type": "objectAttribute",
        "value": {
          "type": "string"
        },
        "optional": true
      },
      "ctaText": {
        "type": "objectAttribute",
        "value": {
          "type": "string"
        },
        "optional": true
      },
      "schedule": {
        "type": "objectAttribute",
        "value": {
          "type": "string"
        },
        "optional": true
      },
      "scheduleType": {
        "type": "objectAttribute",
        "value": {
          "type": "union",
          "of": [
            {
              "type": "string",
              "value": "Annual"
            },
            {
              "type": "string",
              "value": "Monthly"
            },
            {
              "type": "string",
              "value": "Ongoing"
            },
            {
              "type": "string",
              "value": "Weekly"
            }
          ]
        },
        "optional": true
      },
      "status": {
        "type": "objectAttribute",
        "value": {
          "type": "union",
          "of": [
            {
              "type": "string",
              "value": "Active"
            },
            {
              "type": "string",
              "value": "Upcoming"
            }
          ]
        },
        "optional": true
      },
      "sortOrder": {
        "type": "objectAttribute",
        "value": {
          "type": "number"
        },
        "optional": true
      },
      "heroImage": {
        "type": "objectAttribute",
        "value": {
          "type": "object",
          "attributes": {
            "asset": {
              "type": "objectAttribute",
              "value": {
                "type": "inline",
                "name": "sanity.imageAsset.reference"
              },
              "optional": true
            },
            "media": {
              "type": "objectAttribute",
              "value": {
                "type": "unknown"
              },
              "optional": true
            },
            "hotspot": {
              "type": "objectAttribute",
              "value": {
                "type": "inline",
                "name": "sanity.imageHotspot"
              },
              "optional": true
            },
            "crop": {
              "type": "objectAttribute",
              "value": {
                "type": "inline",
                "name": "sanity.imageCrop"
              },
              "optional": true
            },
            "_type": {
              "type": "objectAttribute",
              "value": {
                "type": "string",
                "value": "image"
              }
            }
          }
        },
        "optional": true
      },
      "cardImages": {
        "type": "objectAttribute",
        "value": {
          "type": "array",
          "of": {
            "type": "object",
            "attributes": {
              "asset": {
                "type": "objectAttribute",
                "value": {
                  "type": "inline",
                  "name": "sanity.imageAsset.reference"
                },
                "optional": true
              },
              "media": {
                "type": "objectAttribute",
                "value": {
                  "type": "unknown"
                },
                "optional": true
              },
              "hotspot": {
                "type": "objectAttribute",
                "value": {
                  "type": "inline",
                  "name": "sanity.imageHotspot"
                },
                "optional": true
              },
              "crop": {
                "type": "objectAttribute",
                "value": {
                  "type": "inline",
                  "name": "sanity.imageCrop"
                },
                "optional": true
              },
              "_type": {
                "type": "objectAttribute",
                "value": {
                  "type": "string",
                  "value": "image"
                }
              }
            },
            "rest": {
              "type": "object",
              "attributes": {
                "_key": {
                  "type": "objectAttribute",
                  "value": {
                    "type": "string"
                  }
                }
              }
            }
          }
        },
        "optional": true
      },
      "cardStat": {
        "type": "objectAttribute",
        "value": {
          "type": "string"
        },
        "optional": true
      },
      "icon": {
        "type": "objectAttribute",
        "value": {
          "type": "union",
          "of": [
            {
              "type": "string",
              "value": "fire"
            },
            {
              "type": "string",
              "value": "school"
            },
            {
              "type": "string",
              "value": "youth"
            },
            {
              "type": "string",
              "value": "beach"
            },
            {
              "type": "string",
              "value": "gift"
            },
            {
              "type": "string",
              "value": "wellness"
            },
            {
              "type": "string",
              "value": "food"
            }
          ]
        },
        "optional": true
      },
      "keyPartners": {
        "type": "objectAttribute",
        "value": {
          "type": "string"
        },
        "optional": true
      },
      "notableParticipants": {
        "type": "objectAttribute",
        "value": {
          "type": "string"
        },
        "optional": true
      },
      "videos": {
        "type": "objectAttribute",
        "value": {
          "type": "array",
          "of": {
            "type": "object",
            "attributes": {
              "title": {
                "type": "objectAttribute",
                "value": {
                  "type": "string"
                },
                "optional": true
              },
              "url": {
                "type": "objectAttribute",
                "value": {
                  "type": "string"
                },
                "optional": true
              },
              "caption": {
                "type": "objectAttribute",
                "value": {
                  "type": "string"
                },
                "optional": true
              }
            },
            "rest": {
              "type": "object",
              "attributes": {
                "_key": {
                  "type": "objectAttribute",
                  "value": {
                    "type": "string"
                  }
                }
              }
            }
          }
        },
        "optional": true
      },
      "howItWorks": {
        "type": "objectAttribute",
        "value": {
          "type": "string"
        },
        "optional": true
      },
      "impactStory": {
        "type": "objectAttribute",
        "value": {
          "type": "string"
        },
        "optional": true
      }
    }
  },
  {
    "name": "slug",
    "type": "type",
    "value": {
      "type": "object",
      "attributes": {
        "_type": {
          "type": "objectAttribute",
          "value": {
            "type": "string",
            "value": "slug"
          }
        },
        "current": {
          "type": "objectAttribute",
          "value": {
            "type": "string"
          },
          "optional": true
        },
        "source": {
          "type": "objectAttribute",
          "value": {
            "type": "string"
          },
          "optional": true
        }
      }
    }
  },
  {
    "name": "sanity.imagePaletteSwatch",
    "type": "type",
    "value": {
      "type": "object",
      "attributes": {
        "_type": {
          "type": "objectAttribute",
          "value": {
            "type": "string",
            "value": "sanity.imagePaletteSwatch"
          }
        },
        "background": {
          "type": "objectAttribute",
          "value": {
            "type": "string"
          },
          "optional": true
        },
        "foreground": {
          "type": "objectAttribute",
          "value": {
            "type": "string"
          },
          "optional": true
        },
        "population": {
          "type": "objectAttribute",
          "value": {
            "type": "number"
          },
          "optional": true
        },
        "title": {
          "type": "objectAttribute",
          "value": {
            "type": "string"
          },
          "optional": true
        }
      }
    }
  },
  {
    "name": "sanity.imagePalette",
    "type": "type",
    "value": {
      "type": "object",
      "attributes": {
        "_type": {
          "type": "objectAttribute",
          "value": {
            "type": "string",
            "value": "sanity.imagePalette"
          }
        },
        "darkMuted": {
          "type": "objectAttribute",
          "value": {
            "type": "inline",
            "name": "sanity.imagePaletteSwatch"
          },
          "optional": true
        },
        "lightVibrant": {
          "type": "objectAttribute",
          "value": {
            "type": "inline",
            "name": "sanity.imagePaletteSwatch"
          },
          "optional": true
        },
        "darkVibrant": {
          "type": "objectAttribute",
          "value": {
            "type": "inline",
            "name": "sanity.imagePaletteSwatch"
          },
          "optional": true
        },
        "vibrant": {
          "type": "objectAttribute",
          "value": {
            "type": "inline",
            "name": "sanity.imagePaletteSwatch"
          },
          "optional": true
        },
        "dominant": {
          "type": "objectAttribute",
          "value": {
            "type": "inline",
            "name": "sanity.imagePaletteSwatch"
          },
          "optional": true
        },
        "lightMuted": {
          "type": "objectAttribute",
          "value": {
            "type": "inline",
            "name": "sanity.imagePaletteSwatch"
          },
          "optional": true
        },
        "muted": {
          "type": "objectAttribute",
          "value": {
            "type": "inline",
            "name": "sanity.imagePaletteSwatch"
          },
          "optional": true
        }
      }
    }
  },
  {
    "name": "sanity.imageDimensions",
    "type": "type",
    "value": {
      "type": "object",
      "attributes": {
        "_type": {
          "type": "objectAttribute",
          "value": {
            "type": "string",
            "value": "sanity.imageDimensions"
          }
        },
        "height": {
          "type": "objectAttribute",
          "value": {
            "type": "number"
          },
          "optional": true
        },
        "width": {
          "type": "objectAttribute",
          "value": {
            "type": "number"
          },
          "optional": true
        },
        "aspectRatio": {
          "type": "objectAttribute",
          "value": {
            "type": "number"
          },
          "optional": true
        }
      }
    }
  },
  {
    "name": "sanity.imageMetadata",
    "type": "type",
    "value": {
      "type": "object",
      "attributes": {
        "_type": {
          "type": "objectAttribute",
          "value": {
            "type": "string",
            "value": "sanity.imageMetadata"
          }
        },
        "location": {
          "type": "objectAttribute",
          "value": {
            "type": "inline",
            "name": "geopoint"
          },
          "optional": true
        },
        "dimensions": {
          "type": "objectAttribute",
          "value": {
            "type": "inline",
            "name": "sanity.imageDimensions"
          },
          "optional": true
        },
        "palette": {
          "type": "objectAttribute",
          "value": {
            "type": "inline",
            "name": "sanity.imagePalette"
          },
          "optional": true
        },
        "lqip": {
          "type": "objectAttribute",
          "value": {
            "type": "string"
          },
          "optional": true
        },
        "blurHash": {
          "type": "objectAttribute",
          "value": {
            "type": "string"
          },
          "optional": true
        },
        "thumbHash": {
          "type": "objectAttribute",
          "value": {
            "type": "string"
          },
          "optional": true
        },
        "hasAlpha": {
          "type": "objectAttribute",
          "value": {
            "type": "boolean"
          },
          "optional": true
        },
        "isOpaque": {
          "type": "objectAttribute",
          "value": {
            "type": "boolean"
          },
          "optional": true
        }
      }
    }
  },
  {
    "name": "sanity.fileAsset",
    "type": "document",
    "attributes": {
      "_id": {
        "type": "objectAttribute",
        "value": {
          "type": "string"
        }
      },
      "_type": {
        "type": "objectAttribute",
        "value": {
          "type": "string",
          "value": "sanity.fileAsset"
        }
      },
      "_createdAt": {
        "type": "objectAttribute",
        "value": {
          "type": "string"
        }
      },
      "_updatedAt": {
        "type": "objectAttribute",
        "value": {
          "type": "string"
        }
      },
      "_rev": {
        "type": "objectAttribute",
        "value": {
          "type": "string"
        }
      },
      "originalFilename": {
        "type": "objectAttribute",
        "value": {
          "type": "string"
        },
        "optional": true
      },
      "label": {
        "type": "objectAttribute",
        "value": {
          "type": "string"
        },
        "optional": true
      },
      "title": {
        "type": "objectAttribute",
        "value": {
          "type": "string"
        },
        "optional": true
      },
      "description": {
        "type": "objectAttribute",
        "value": {
          "type": "string"
        },
        "optional": true
      },
      "altText": {
        "type": "objectAttribute",
        "value": {
          "type": "string"
        },
        "optional": true
      },
      "sha1hash": {
        "type": "objectAttribute",
        "value": {
          "type": "string"
        },
        "optional": true
      },
      "extension": {
        "type": "objectAttribute",
        "value": {
          "type": "string"
        },
        "optional": true
      },
      "mimeType": {
        "type": "objectAttribute",
        "value": {
          "type": "string"
        },
        "optional": true
      },
      "size": {
        "type": "objectAttribute",
        "value": {
          "type": "number"
        },
        "optional": true
      },
      "assetId": {
        "type": "objectAttribute",
        "value": {
          "type": "string"
        },
        "optional": true
      },
      "uploadId": {
        "type": "objectAttribute",
        "value": {
          "type": "string"
        },
        "optional": true
      },
      "path": {
        "type": "objectAttribute",
        "value": {
          "type": "string"
        },
        "optional": true
      },
      "url": {
        "type": "objectAttribute",
        "value": {
          "type": "string"
        },
        "optional": true
      },
      "source": {
        "type": "objectAttribute",
        "value": {
          "type": "inline",
          "name": "sanity.assetSourceData"
        },
        "optional": true
      }
    }
  },
  {
    "name": "sanity.assetSourceData",
    "type": "type",
    "value": {
      "type": "object",
      "attributes": {
        "_type": {
          "type": "objectAttribute",
          "value": {
            "type": "string",
            "value": "sanity.assetSourceData"
          }
        },
        "name": {
          "type": "objectAttribute",
          "value": {
            "type": "string"
          },
          "optional": true
        },
        "id": {
          "type": "objectAttribute",
          "value": {
            "type": "string"
          },
          "optional": true
        },
        "url": {
          "type": "objectAttribute",
          "value": {
            "type": "string"
          },
          "optional": true
        }
      }
    }
  },
  {
    "name": "sanity.imageAsset",
    "type": "document",
    "attributes": {
      "_id": {
        "type": "objectAttribute",
        "value": {
          "type": "string"
        }
      },
      "_type": {
        "type": "objectAttribute",
        "value": {
          "type": "string",
          "value": "sanity.imageAsset"
        }
      },
      "_createdAt": {
        "type": "objectAttribute",
        "value": {
          "type": "string"
        }
      },
      "_updatedAt": {
        "type": "objectAttribute",
        "value": {
          "type": "string"
        }
      },
      "_rev": {
        "type": "objectAttribute",
        "value": {
          "type": "string"
        }
      },
      "originalFilename": {
        "type": "objectAttribute",
        "value": {
          "type": "string"
        },
        "optional": true
      },
      "label": {
        "type": "objectAttribute",
        "value": {
          "type": "string"
        },
        "optional": true
      },
      "title": {
        "type": "objectAttribute",
        "value": {
          "type": "string"
        },
        "optional": true
      },
      "description": {
        "type": "objectAttribute",
        "value": {
          "type": "string"
        },
        "optional": true
      },
      "altText": {
        "type": "objectAttribute",
        "value": {
          "type": "string"
        },
        "optional": true
      },
      "sha1hash": {
        "type": "objectAttribute",
        "value": {
          "type": "string"
        },
        "optional": true
      },
      "extension": {
        "type": "objectAttribute",
        "value": {
          "type": "string"
        },
        "optional": true
      },
      "mimeType": {
        "type": "objectAttribute",
        "value": {
          "type": "string"
        },
        "optional": true
      },
      "size": {
        "type": "objectAttribute",
        "value": {
          "type": "number"
        },
        "optional": true
      },
      "assetId": {
        "type": "objectAttribute",
        "value": {
          "type": "string"
        },
        "optional": true
      },
      "uploadId": {
        "type": "objectAttribute",
        "value": {
          "type": "string"
        },
        "optional": true
      },
      "path": {
        "type": "objectAttribute",
        "value": {
          "type": "string"
        },
        "optional": true
      },
      "url": {
        "type": "objectAttribute",
        "value": {
          "type": "string"
        },
        "optional": true
      },
      "metadata": {
        "type": "objectAttribute",
        "value": {
          "type": "inline",
          "name": "sanity.imageMetadata"
        },
        "optional": true
      },
      "source": {
        "type": "objectAttribute",
        "value": {
          "type": "inline",
          "name": "sanity.assetSourceData"
        },
        "optional": true
      }
    }
  },
  {
    "name": "geopoint",
    "type": "type",
    "value": {
      "type": "object",
      "attributes": {
        "_type": {
          "type": "objectAttribute",
          "value": {
            "type": "string",
            "value": "geopoint"
          }
        },
        "lat": {
          "type": "objectAttribute",
          "value": {
            "type": "number"
          },
          "optional": true
        },
        "lng": {
          "type": "objectAttribute",
          "value": {
            "type": "number"
          },
          "optional": true
        },
        "alt": {
          "type": "objectAttribute",
          "value": {
            "type": "number"
          },
          "optional": true
        }
      }
    }
  }
]
